agentserver/__init__.py
agentserver/admin.py
agentserver/echo.py
agentserver/server.py
agentserver/agents/__init__.py
agentserver/agents/supervisoragent.py
agentserver/clients/__init__.py
agentserver/clients/constants.py
agentserver/clients/supervisorclient.py
agentserver/clients/supervisorclientcoordinator.py
agentserver/config/__init__.py
agentserver/config/admin.py
agentserver/config/server.py
agentserver/data/conf/agentserver.conf
agentserver/data/conf/mysql-example.conf
agentserver/data/conf/postgres-example.conf
agentserver/data/conf/sqlite-example.conf
agentserver/data/supervisor/agentserver.conf
agentserver/db/__init__.py
agentserver/db/models.py
agentserver/db/timeseries.py
agentserver/http/__init__.py
agentserver/http/agent.py
agentserver/http/base.py
agentserver/http/client.py
agentserver/utils/__init__.py
agentserver/utils/haiku.py
agentserver/utils/ip.py
agentserver/utils/log.py
agentserver/utils/uuid.py
agentserver/utils/validators.py
agentserver/ws/__init__.py
agentserver/ws/agent.py
agentserver/ws/base.py
agentserver/ws/client.py
agentserver-0.0.1.dev3.dist-info/DESCRIPTION.rst
agentserver-0.0.1.dev3.dist-info/METADATA
agentserver-0.0.1.dev3.dist-info/RECORD
agentserver-0.0.1.dev3.dist-info/WHEEL
agentserver-0.0.1.dev3.dist-info/dependency_links.txt
agentserver-0.0.1.dev3.dist-info/entry_points.txt
agentserver-0.0.1.dev3.dist-info/metadata.json
agentserver-0.0.1.dev3.dist-info/top_level.txt
