Metadata-Version: 2.0
Name: agentserver
Version: 0.0.1.dev3
Summary: A server for managing monitoring agents
Home-page: https://github.com/silverfernsys/agentserver
Author: Silver Fern Systems
Author-email: dev@silverfern.io
License: BSD
Keywords: monitoring development
Platform: UNKNOWN
Classifier: Development Status :: 3 - Alpha
Classifier: Intended Audience :: Developers
Classifier: Topic :: Software Development :: Build Tools
Classifier: License :: OSI Approved :: BSD License
Classifier: Programming Language :: Python :: 2.7
Requires-Dist: Cerberus (==0.9.2)
Requires-Dist: configutil
Requires-Dist: iso8601utils
Requires-Dist: passlib
Requires-Dist: pyfiglet
Requires-Dist: setproctitle
Requires-Dist: sqlalchemy
Requires-Dist: tabulate
Requires-Dist: termcolor
Requires-Dist: tornado
Provides-Extra: druid
Requires-Dist: kafka-python; extra == 'druid'
Requires-Dist: pydruid; extra == 'druid'
Provides-Extra: mysql
Requires-Dist: PyMySQL; extra == 'mysql'
Provides-Extra: postgres
Requires-Dist: psycopg2; extra == 'postgres'
Provides-Extra: test
Requires-Dist: codecov; extra == 'test'
Requires-Dist: coverage; extra == 'test'
Requires-Dist: mock; extra == 'test'
Requires-Dist: pytest; extra == 'test'
